students2courses/__init__.py
students2courses/course_capacities.csv
students2courses/examples.py
students2courses/solver.py
students2courses/student_votes.csv
students2courses/tests/__init__.py
students2courses/tests/course_capacities.csv
students2courses/tests/student_votes.csv
students2courses/tests/test_solver.py
students2courses-1.0.0.dist-info/METADATA
students2courses-1.0.0.dist-info/WHEEL
students2courses-1.0.0.dist-info/licenses/LICENSE
students2courses-1.0.0.dist-info/RECORD
