Metadata-Version: 2.1
Name: students2courses
Version: 1.0.0
Summary: Solves the following problem: Students choose their course preferences from a set of courses. Assign a course to each student so that as many wishes as possible are fulfilled.
Project-URL: Homepage, https://github.com/oceanwhiskey/students2courses
Project-URL: Bug Tracker, https://github.com/oceanwhiskey/students2courses/issues
Author-email: Ingo Wilms <ingo.wilms@gmail.com>
License: Copyright (c) 2022 Ingo Wilms
License-File: LICENSE
Classifier: License :: OSI Approved :: MIT License
Classifier: Operating System :: OS Independent
Classifier: Programming Language :: Python :: 3
Requires-Python: >=3.7
